{"plates": {"1": {"plate_number": "9110", "entry_time": "2025-06-06T00:03:20.047651", "exit_time": null, "fee": null}, "2": {"plate_number": "919", "entry_time": "2025-06-06T00:03:24.573644", "exit_time": null, "fee": null}, "3": {"plate_number": "9119", "entry_time": "2025-06-06T00:03:38.856091", "exit_time": null, "fee": null}, "4": {"plate_number": "\u0e01\u0e2d9119", "entry_time": "2025-06-06T00:04:06.658503", "exit_time": "2025-06-06T00:04:15.648115", "fee": 20.0}, "5": {"plate_number": "\u0e01\u0e2d9119", "entry_time": "2025-06-06T00:06:18.874815", "exit_time": "2025-06-06T00:06:29.799144", "fee": 20.0}, "6": {"plate_number": "\u0e01\u0e2d9119", "entry_time": "2025-06-06T00:07:28.733966", "exit_time": "2025-06-06T00:07:34.953268", "fee": 20.0}}}